scikit_learn_extra-0.3.0.dist-info/LICENSE
scikit_learn_extra-0.3.0.dist-info/WHEEL
scikit_learn_extra-0.3.0.dist-info/top_level.txt
scikit_learn_extra-0.3.0.dist-info/RECORD
scikit_learn_extra-0.3.0.dist-info/METADATA
sklearn_extra/__init__.py
sklearn_extra/_version.py
sklearn_extra/robust/mean_estimators.py
sklearn_extra/robust/__init__.py
sklearn_extra/robust/_robust_weighted_estimator_helper.cpython-38-x86_64-linux-gnu.so
sklearn_extra/robust/robust_weighted_estimator.py
sklearn_extra/kernel_methods/__init__.py
sklearn_extra/kernel_methods/_eigenpro.py
sklearn_extra/kernel_methods/tests/__init__.py
sklearn_extra/kernel_methods/tests/test_eigenpro.py
sklearn_extra/tests/test_common.py
sklearn_extra/tests/__init__.py
sklearn_extra/kernel_approximation/_fastfood.py
sklearn_extra/kernel_approximation/__init__.py
sklearn_extra/kernel_approximation/test_fastfood.py
sklearn_extra/kernel_approximation/tests/__init__.py
sklearn_extra/utils/_cyfht.cpython-38-x86_64-linux-gnu.so
sklearn_extra/cluster/_k_medoids_helper.cpython-38-x86_64-linux-gnu.so
sklearn_extra/cluster/_commonnn.py
sklearn_extra/cluster/_k_medoids.py
sklearn_extra/cluster/__init__.py
sklearn_extra/cluster/_commonnn_inner.cpython-38-x86_64-linux-gnu.so
sklearn_extra/cluster/tests/__init__.py
sklearn_extra/cluster/tests/test_commonnn.py
sklearn_extra/cluster/tests/test_k_medoids.py
benchmarks/__init__.py
benchmarks/bench_rbfsampler_fastfood.py
benchmarks/_bench/__init__.py
benchmarks/_bench/robust_plot_synthetic.py
benchmarks/_bench/eigenpro_plot_noisy_mnist.py
benchmarks/_bench/eigenpro_plot_synthetic.py
benchmarks/_bench/eigenpro_plot_mnist.py
