Metadata-Version: 2.1
Name: scikit-learn-extra
Version: 0.3.0
Summary: A set of tools for scikit-learn.
Home-page: https://github.com/scikit-learn-contrib/scikit-learn-extra
License: new BSD
Download-URL: https://github.com/scikit-learn-contrib/scikit-learn-extra
Platform: UNKNOWN
Classifier: Intended Audience :: Science/Research
Classifier: Intended Audience :: Developers
Classifier: License :: OSI Approved
Classifier: Programming Language :: Python
Classifier: Topic :: Software Development
Classifier: Topic :: Scientific/Engineering
Classifier: Operating System :: Microsoft :: Windows
Classifier: Operating System :: POSIX
Classifier: Operating System :: Unix
Classifier: Operating System :: MacOS
Classifier: Programming Language :: Python :: 3.6
Classifier: Programming Language :: Python :: 3.7
Classifier: Programming Language :: Python :: 3.8
Classifier: Programming Language :: Python :: 3.9
Classifier: Programming Language :: Python :: Implementation :: CPython
Requires-Python: >=3.6
Provides-Extra: tests
Provides-Extra: docs
